{
  "type": "railcraft:crusher",
  "conditions": [
    {
      "type": "forge:not",
      "value": {
        "type": "forge:tag_empty",
        "tag": "forge:ores/salt"
      }
    }
  ],
  "ingredient": {
    "tag": "forge:ores/salt"
  },
  "outputs": [
    {
      "count": 3,
      "probability": 1.0,
      "result": {
        "item": "railcraft:saltpeter_dust"
      }
    },
    {
      "count": 1,
      "probability": 0.85,
      "result": {
        "item": "railcraft:saltpeter_dust"
      }
    },
    {
      "count": 1,
      "probability": 0.35,
      "result": {
        "item": "railcraft:saltpeter_dust"
      }
    }
  ],
  "processTime": 200
}