{
  "parent": "railcraft:carts/root",
  "display": {
    "icon": {
      "item": "railcraft:steam_locomotive"
    },
    "title": {
      "translate": "advancements.railcraft.carts.locomotive.name"
    },
    "description": {
      "translate": "advancements.railcraft.carts.locomotive.desc"
    },
    "frame": "challenge",
    "show_toast": true,
    "announce_to_chat": true,
    "hidden": false
  },
  "criteria": {
    "has_locomotives": {
      "trigger": "minecraft:inventory_changed",
      "conditions": {
        "items": [
          {
            "item": "railcraft:steam_locomotive"
          }
        ]
      }
    }
  },
  "requirements": [
    [
      "has_locomotives"
    ]
  ]
}