{
  "variants": {
    "mirrored=false,switched=false,facing=north": {
      "model": "railcraft:block/turnout_track_north"
    },
    "mirrored=false,switched=true,facing=north": {
      "model": "railcraft:block/turnout_track_north_switched"
    },
    "mirrored=false,switched=false,facing=south": {
      "model": "railcraft:block/turnout_track_north",
      "y": 180
    },
    "mirrored=false,switched=true,facing=south": {
      "model": "railcraft:block/turnout_track_north_switched",
      "y": 180
    },
    "mirrored=true,switched=false,facing=north": {
      "model": "railcraft:block/turnout_track_south",
      "y": 180
    },
    "mirrored=true,switched=true,facing=north": {
      "model": "railcraft:block/turnout_track_south_switched",
      "y": 180
    },
    "mirrored=true,switched=false,facing=south": {
      "model": "railcraft:block/turnout_track_south"
    },
    "mirrored=true,switched=true,facing=south": {
      "model": "railcraft:block/turnout_track_south_switched"
    },
    "mirrored=false,switched=false,facing=east": {
      "model": "railcraft:block/turnout_track_north",
      "y": 90
    },
    "mirrored=false,switched=true,facing=east": {
      "model": "railcraft:block/turnout_track_north_switched",
      "y": 90
    },
    "mirrored=false,switched=false,facing=west": {
      "model": "railcraft:block/turnout_track_north",
      "y": 270
    },
    "mirrored=false,switched=true,facing=west": {
      "model": "railcraft:block/turnout_track_north_switched",
      "y": 270
    },
    "mirrored=true,switched=false,facing=east": {
      "model": "railcraft:block/turnout_track_south",
      "y": 270
    },
    "mirrored=true,switched=true,facing=east": {
      "model": "railcraft:block/turnout_track_south_switched",
      "y": 270
    },
    "mirrored=true,switched=false,facing=west": {
      "model": "railcraft:block/turnout_track_south",
      "y": 90
    },
    "mirrored=true,switched=true,facing=west": {
      "model": "railcraft:block/turnout_track_south_switched",
      "y": 90
    }
  }
}